<annotation>
    <annotator>CR</annotator>
    <folder>Photos 2</folder>
    <filename>KAD17-003_Bx21-25_67.69-81.15m_DxO.jpg</filename>
    <size>
        <width>3456</width>
        <height>2304</height>
        <depth>3</depth>
    </size>
    <segmented>0</segmented>
    <object>
        <name>rock-KAD17_003-81-81.15</name>
        <pose>Unspecified</pose>
        <truncated>0</truncated>
        <occluded>0</occluded>
        <difficult>0</difficult>
        <bndbox>
            <xmin>2974</xmin>
            <ymin>1791</ymin>
            <xmax>3333</xmax>
            <ymax>1923</ymax>
        </bndbox>
    </object>
    <object>
        <name>rock-KAD17_003-80-81</name>
        <pose>Unspecified</pose>
        <truncated>0</truncated>
        <occluded>0</occluded>
        <difficult>0</difficult>
        <rotated_box>
            <cx>1818</cx>
            <cy>1844</cy>
            <width>2085</width>
            <height>127</height>
            <rot>6.276742</rot>
        </rotated_box>
        <polygon>
            <x1>776</x1>
            <y1>1901</y1>
            <x2>2860</x2>
            <y2>1914</y2>
            <x3>2860</x3>
            <y3>1788</y3>
            <x4>777</x4>
            <y4>1775</y4>
        </polygon>
        <bndbox>
            <xmin>776</xmin>
            <ymin>1775</ymin>
            <xmax>2860</xmax>
            <ymax>1914</ymax>
        </bndbox>
    </object>
    <object>
        <name>rock-KAD17_003-79x-80</name>
        <pose>Unspecified</pose>
        <truncated>0</truncated>
        <occluded>0</occluded>
        <difficult>0</difficult>
        <rotated_box>
            <cx>551</cx>
            <cy>1832</cy>
            <width>442</width>
            <height>121</height>
            <rot>6.271662</rot>
        </rotated_box>
        <polygon>
            <x1>330</x1>
            <y1>1889</y1>
            <x2>771</x2>
            <y2>1894</y2>
            <x3>772</x3>
            <y3>1775</y3>
            <x4>331</x4>
            <y4>1770</y4>
        </polygon>
        <bndbox>
            <xmin>330</xmin>
            <ymin>1770</ymin>
            <xmax>772</xmax>
            <ymax>1894</ymax>
        </bndbox>
    </object>
    <object>
        <name>rock-KAD17_003-79-79x</name>
        <pose>Unspecified</pose>
        <truncated>0</truncated>
        <occluded>0</occluded>
        <difficult>0</difficult>
        <rotated_box>
            <cx>2323</cx>
            <cy>1699</cy>
            <width>1620</width>
            <height>120</height>
            <rot>6.278915</rot>
        </rotated_box>
        <polygon>
            <x1>1513</x1>
            <y1>1755</y1>
            <x2>3132</x2>
            <y2>1762</y2>
            <x3>3133</x3>
            <y3>1643</y3>
            <x4>1514</x4>
            <y4>1636</y4>
        </polygon>
        <bndbox>
            <xmin>1513</xmin>
            <ymin>1636</ymin>
            <xmax>3133</xmax>
            <ymax>1762</ymax>
        </bndbox>
    </object>
    <object>
        <name>rock-KAD17_003-78x-79</name>
        <pose>Unspecified</pose>
        <truncated>0</truncated>
        <occluded>0</occluded>
        <difficult>0</difficult>
        <rotated_box>
            <cx>917</cx>
            <cy>1685</cy>
            <width>1181</width>
            <height>121</height>
            <rot>6.271405</rot>
        </rotated_box>
        <polygon>
            <x1>327</x1>
            <y1>1738</y1>
            <x2>1507</x2>
            <y2>1752</y2>
            <x3>1508</x3>
            <y3>1632</y3>
            <x4>328</x4>
            <y4>1618</y4>
        </polygon>
        <bndbox>
            <xmin>327</xmin>
            <ymin>1618</ymin>
            <xmax>1508</xmax>
            <ymax>1752</ymax>
        </bndbox>
    </object>
    <object>
        <name>rock-KAD17_003-78-78x</name>
        <pose>Unspecified</pose>
        <truncated>0</truncated>
        <occluded>0</occluded>
        <difficult>0</difficult>
        <bndbox>
            <xmin>2390</xmin>
            <ymin>1420</ymin>
            <xmax>3352</xmax>
            <ymax>1548</ymax>
        </bndbox>
    </object>
    <object>
        <name>rock-KAD17_003-77x-78</name>
        <pose>Unspecified</pose>
        <truncated>0</truncated>
        <occluded>0</occluded>
        <difficult>0</difficult>
        <rotated_box>
            <cx>1269</cx>
            <cy>1481</cy>
            <width>1912</width>
            <height>125</height>
            <rot>6.279062</rot>
        </rotated_box>
        <polygon>
            <x1>314</x1>
            <y1>1539</y1>
            <x2>2225</x2>
            <y2>1547</y2>
            <x3>2226</x3>
            <y3>1423</y3>
            <x4>314</x4>
            <y4>1416</y4>
        </polygon>
        <bndbox>
            <xmin>314</xmin>
            <ymin>1416</ymin>
            <xmax>2226</xmax>
            <ymax>1547</ymax>
        </bndbox>
    </object>
    <object>
        <name>rock-KAD17_003-77-77x</name>
        <pose>Unspecified</pose>
        <truncated>0</truncated>
        <occluded>0</occluded>
        <difficult>0</difficult>
        <bndbox>
            <xmin>2383</xmin>
            <ymin>1268</ymin>
            <xmax>3351</xmax>
            <ymax>1382</ymax>
        </bndbox>
    </object>
    <object>
        <name>rock-KAD17_003-76-77</name>
        <pose>Unspecified</pose>
        <truncated>0</truncated>
        <occluded>0</occluded>
        <difficult>0</difficult>
        <bndbox>
            <xmin>347</xmin>
            <ymin>1268</ymin>
            <xmax>2381</xmax>
            <ymax>1391</ymax>
        </bndbox>
    </object>
    <object>
        <name>rock-KAD17_003-75-76</name>
        <pose>Unspecified</pose>
        <truncated>0</truncated>
        <occluded>0</occluded>
        <difficult>0</difficult>
        <rotated_box>
            <cx>2307</cx>
            <cy>1109</cy>
            <width>1971</width>
            <height>125</height>
            <rot>0.004013</rot>
        </rotated_box>
        <polygon>
            <x1>1322</x1>
            <y1>1176</y1>
            <x2>3293</x2>
            <y2>1168</y2>
            <x3>3292</x3>
            <y3>1043</y3>
            <x4>1322</x4>
            <y4>1051</y4>
        </polygon>
        <bndbox>
            <xmin>1322</xmin>
            <ymin>1043</ymin>
            <xmax>3293</xmax>
            <ymax>1176</ymax>
        </bndbox>
    </object>
    <object>
        <name>rock-KAD17_003-74x-75</name>
        <pose>Unspecified</pose>
        <truncated>0</truncated>
        <occluded>0</occluded>
        <difficult>0</difficult>
        <bndbox>
            <xmin>331</xmin>
            <ymin>1046</ymin>
            <xmax>1232</xmax>
            <ymax>1175</ymax>
        </bndbox>
    </object>
    <object>
        <name>rock-KAD17_003-74-74x</name>
        <pose>Unspecified</pose>
        <truncated>0</truncated>
        <occluded>0</occluded>
        <difficult>0</difficult>
        <rotated_box>
            <cx>2665</cx>
            <cy>949</cy>
            <width>1182</width>
            <height>124</height>
            <rot>0.011118</rot>
        </rotated_box>
        <polygon>
            <x1>2075</x1>
            <y1>1018</y1>
            <x2>3256</x2>
            <y2>1004</y2>
            <x3>3255</x3>
            <y3>882</y3>
            <x4>2074</x4>
            <y4>895</y4>
        </polygon>
        <bndbox>
            <xmin>2074</xmin>
            <ymin>882</ymin>
            <xmax>3256</xmax>
            <ymax>1018</ymax>
        </bndbox>
    </object>
    <object>
        <name>rock-KAD17_003-73x-74</name>
        <pose>Unspecified</pose>
        <truncated>0</truncated>
        <occluded>0</occluded>
        <difficult>0</difficult>
        <bndbox>
            <xmin>326</xmin>
            <ymin>890</ymin>
            <xmax>2070</xmax>
            <ymax>1011</ymax>
        </bndbox>
    </object>
    <object>
        <name>rock-KAD17_003-73-73x</name>
        <pose>Unspecified</pose>
        <truncated>0</truncated>
        <occluded>0</occluded>
        <difficult>0</difficult>
        <bndbox>
            <xmin>3061</xmin>
            <ymin>648</ymin>
            <xmax>3363</xmax>
            <ymax>776</ymax>
        </bndbox>
    </object>
    <object>
        <name>rock-KAD17_003-72-73</name>
        <pose>Unspecified</pose>
        <truncated>0</truncated>
        <occluded>0</occluded>
        <difficult>0</difficult>
        <rotated_box>
            <cx>2018</cx>
            <cy>727</cy>
            <width>2079</width>
            <height>127</height>
            <rot>0.011486</rot>
        </rotated_box>
        <polygon>
            <x1>981</x1>
            <y1>802</y1>
            <x2>3058</x2>
            <y2>778</y2>
            <x3>3057</x3>
            <y3>653</y3>
            <x4>979</x4>
            <y4>676</y4>
        </polygon>
        <bndbox>
            <xmin>979</xmin>
            <ymin>653</ymin>
            <xmax>3058</xmax>
            <ymax>802</ymax>
        </bndbox>
    </object>
    <object>
        <name>rock-KAD17_003-71x-72</name>
        <pose>Unspecified</pose>
        <truncated>0</truncated>
        <occluded>0</occluded>
        <difficult>0</difficult>
        <rotated_box>
            <cx>609</cx>
            <cy>742</cy>
            <width>625</width>
            <height>119</height>
            <rot>0.013474</rot>
        </rotated_box>
        <polygon>
            <x1>298</x1>
            <y1>805</y1>
            <x2>922</x2>
            <y2>797</y2>
            <x3>921</x3>
            <y3>679</y3>
            <x4>296</x4>
            <y4>687</y4>
        </polygon>
        <bndbox>
            <xmin>296</xmin>
            <ymin>679</ymin>
            <xmax>922</xmax>
            <ymax>805</ymax>
        </bndbox>
    </object>
    <object>
        <name>rock-KAD17_003-71-71x</name>
        <pose>Unspecified</pose>
        <truncated>0</truncated>
        <occluded>0</occluded>
        <difficult>0</difficult>
        <rotated_box>
            <cx>2603</cx>
            <cy>554</cy>
            <width>1525</width>
            <height>117</height>
            <rot>0.009204</rot>
        </rotated_box>
        <polygon>
            <x1>1842</x1>
            <y1>619</y1>
            <x2>3367</x2>
            <y2>605</y2>
            <x3>3365</x3>
            <y3>489</y3>
            <x4>1841</x4>
            <y4>503</y4>
        </polygon>
        <bndbox>
            <xmin>1841</xmin>
            <ymin>489</ymin>
            <xmax>3367</xmax>
            <ymax>619</ymax>
        </bndbox>
    </object>
    <object>
        <name>rock-KAD17_003-70x-71</name>
        <pose>Unspecified</pose>
        <truncated>0</truncated>
        <occluded>0</occluded>
        <difficult>0</difficult>
        <rotated_box>
            <cx>1073</cx>
            <cy>576</cy>
            <width>1520</width>
            <height>112</height>
            <rot>0.014211</rot>
        </rotated_box>
        <polygon>
            <x1>315</x1>
            <y1>643</y1>
            <x2>1834</x2>
            <y2>621</y2>
            <x3>1832</x3>
            <y3>510</y3>
            <x4>314</x4>
            <y4>531</y4>
        </polygon>
        <bndbox>
            <xmin>314</xmin>
            <ymin>510</ymin>
            <xmax>1834</xmax>
            <ymax>643</ymax>
        </bndbox>
    </object>
    <object>
        <name>rock-KAD17_003-70-70x</name>
        <pose>Unspecified</pose>
        <truncated>0</truncated>
        <occluded>0</occluded>
        <difficult>0</difficult>
        <rotated_box>
            <cx>2982</cx>
            <cy>333</cy>
            <width>572</width>
            <height>130</height>
            <rot>0.013548</rot>
        </rotated_box>
        <polygon>
            <x1>2698</x1>
            <y1>401</y1>
            <x2>3269</x2>
            <y2>394</y2>
            <x3>3268</x3>
            <y3>265</y3>
            <x4>2696</x4>
            <y4>272</y4>
        </polygon>
        <bndbox>
            <xmin>2696</xmin>
            <ymin>265</ymin>
            <xmax>3269</xmax>
            <ymax>401</ymax>
        </bndbox>
    </object>
    <object>
        <name>rock-KAD17_003-69-70</name>
        <pose>Unspecified</pose>
        <truncated>0</truncated>
        <occluded>0</occluded>
        <difficult>0</difficult>
        <rotated_box>
            <cx>1666</cx>
            <cy>354</cy>
            <width>2064</width>
            <height>122</height>
            <rot>0.015867</rot>
        </rotated_box>
        <polygon>
            <x1>636</x1>
            <y1>431</y1>
            <x2>2698</x2>
            <y2>398</y2>
            <x3>2696</x3>
            <y3>277</y3>
            <x4>634</x4>
            <y4>310</y4>
        </polygon>
        <bndbox>
            <xmin>634</xmin>
            <ymin>277</ymin>
            <xmax>2698</xmax>
            <ymax>431</ymax>
        </bndbox>
    </object>
    <object>
        <name>rock-KAD17_003-68x-69</name>
        <pose>Unspecified</pose>
        <truncated>0</truncated>
        <occluded>0</occluded>
        <difficult>0</difficult>
        <rotated_box>
            <cx>416</cx>
            <cy>373</cy>
            <width>278</width>
            <height>126</height>
            <rot>0.023157</rot>
        </rotated_box>
        <polygon>
            <x1>279</x1>
            <y1>439</y1>
            <x2>556</x2>
            <y2>432</y2>
            <x3>553</x3>
            <y3>308</y3>
            <x4>276</x4>
            <y4>314</y4>
        </polygon>
        <bndbox>
            <xmin>276</xmin>
            <ymin>308</ymin>
            <xmax>556</xmax>
            <ymax>439</ymax>
        </bndbox>
    </object>
    <object>
        <name>rock-KAD17_003-68-68x</name>
        <pose>Unspecified</pose>
        <truncated>0</truncated>
        <occluded>0</occluded>
        <difficult>0</difficult>
        <rotated_box>
            <cx>1964</cx>
            <cy>185</cy>
            <width>2223</width>
            <height>117</height>
            <rot>0.016603</rot>
        </rotated_box>
        <polygon>
            <x1>855</x1>
            <y1>261</y1>
            <x2>3076</x2>
            <y2>225</y2>
            <x3>3075</x3>
            <y3>109</y3>
            <x4>853</x4>
            <y4>146</y4>
        </polygon>
        <bndbox>
            <xmin>853</xmin>
            <ymin>109</ymin>
            <xmax>3076</xmax>
            <ymax>261</ymax>
        </bndbox>
    </object>
    <object>
        <name>rock-KAD17_003-67.69-68</name>
        <pose>Unspecified</pose>
        <truncated>0</truncated>
        <occluded>0</occluded>
        <difficult>0</difficult>
        <rotated_box>
            <cx>562</cx>
            <cy>207</cy>
            <width>575</width>
            <height>120</height>
            <rot>0.016236</rot>
        </rotated_box>
        <polygon>
            <x1>276</x1>
            <y1>271</y1>
            <x2>850</x2>
            <y2>262</y2>
            <x3>848</x3>
            <y3>143</y3>
            <x4>274</x4>
            <y4>153</y4>
        </polygon>
        <bndbox>
            <xmin>274</xmin>
            <ymin>143</ymin>
            <xmax>850</xmax>
            <ymax>271</ymax>
        </bndbox>
    </object>
</annotation>